visor/__init__.py
visor/visor.py
kais_kit_visor_R02-0.0.1.dist-info/METADATA
kais_kit_visor_R02-0.0.1.dist-info/WHEEL
kais_kit_visor_R02-0.0.1.dist-info/top_level.txt
kais_kit_visor_R02-0.0.1.dist-info/RECORD
